{"code": "0000", "message": "\u6210\u529f", "data": {"school_id": "1631", "data_code": "152002600", "name": "\u5305\u5934\u94a2\u94c1\u804c\u4e1a\u6280\u672f\u5b66\u9662", "type": "5001", "school_type": "6001", "school_nature": "36000", "level": "2002", "code_enroll": "1386400", "belong": "\u5185\u8499\u53e4\u81ea\u6cbb\u533a", "f985": "2", "f211": "2", "department": "2", "admissions": "2", "central": "2", "dual_class": "38003", "is_seal": "1", "applied_grade": "0", "num_subject": "0", "num_master": "0", "num_doctor": "0", "num_academician": "0", "num_library": "0", "num_lab": "0", "province_id": "15", "city_id": "1502", "county_id": "0", "is_ads": "2", "is_recruitment": "1", "create_date": "1979", "area": 240, "old_name": "", "status": "1", "add_id": "0", "add_time": "2018-12-08 17:23:23", "update_id": "0", "update_time": "2022-06-04 15:30:49", "ad_level": "3", "short": "", "e_pc": "1", "e_app": "1", "ruanke_rank": "0", "single": "75001", "colleges_level": "", "doublehigh": "0", "wsl_rank": "0", "qs_rank": "0", "xyh_rank": "0", "is_sell": "2", "eol_rank": "2028", "school_batch": "10", "us_rank": "0", "is_logo": "1", "num_master2": "0", "num_doctor2": "0", "ai_status": "1", "is_ads2": "1", "coop_money": "14000.00", "bdold_name": "", "logo": "\\/app\\/html\\/upload\\/logo\\/1631.jpg", "level_name": "\u4e13\u79d1\uff08\u9ad8\u804c\uff09", "type_name": "\u7406\u5de5\u7c7b", "school_type_name": "\u4e13\u79d1\uff08\u9ad8\u804c\uff09", "school_nature_name": "\u516c\u529e", "dual_class_name": "", "xueke_rank": {}, "province_single": {"15": "75001"}, "single_year": 2021, "remark": [], "province_name": "\u5185\u8499\u53e4", "city_name": "\u5305\u5934\u5e02", "town_name": "", "weiwangzhan": "", "urllinks": {"71013": {"school_id": "1631", "link": "http:\\/\\/map.baidu.com\\/?panoid=1001330000150410114044759IN&pid=1001330000150410114044759IN&panotype=street&heading=0&pitch=0", "type": "71013", "img_url": "", "title": ""}, "71009": {"school_id": "1631", "link": "http:\\/\\/zs.btsvc.edu.cn\\/default.html", "type": "71009", "img_url": "", "title": ""}, "71012": {"school_id": "1631", "link": "http:\\/\\/zs.btsvc.edu.cn\\/default.html", "type": "71012", "img_url": "", "title": ""}, "71008": {"school_id": "1631", "link": "http:\\/\\/zs.btsvc.edu.cn\\/default.html", "type": "71008", "img_url": "", "title": ""}, "71007": {"school_id": "1631", "link": "https:\\/\\/www.nm.zsks.cn\\/", "type": "71007", "img_url": "", "title": ""}, "71006": {"school_id": "1631", "link": "https:\\/\\/s95.cnzz.com\\/z_stat.php?id=1254895396&web_id=1254895396", "type": "71006", "img_url": "", "title": ""}}, "yjszs": "", "xiaoyuan": "", "email": "bgyzb@163.com", "school_email": "", "address": "\u5185\u8499\u53e4\u81ea\u6cbb\u533a\u5305\u5934\u5e02\u6606\u533a\u963f\u5c14\u4e01\u5927\u885776\u53f7", "postcode": "014010", "site": "http:\\/\\/zs.btsvc.edu.cn\\/default.html", "school_site": "http:\\/\\/www.btsvc.edu.cn\\/default.html", "phone": "0472-2897332,0472-2897223", "school_phone": "", "miniprogram": "", "content": "\u5305\u5934\u94a2\u94c1\u804c\u4e1a\u6280\u672f\u5b66\u9662\u5750\u843d\u4e8e\u9996\u6279\u5168\u56fd\u6587\u660e\u57ce\u5e02\u3001\u7f8e\u4e3d\u7684\u8349\u539f\u94a2\u57ce\u5305\u5934\u5e02\uff0c\u7531\u5305\u94a2\uff08\u96c6\u56e2\uff09\u516c\u53f8\u51fa\u8d44\u5174\u529e\uff0c\u4e8e2005\u5e74\u7ecf\u5185\u8499\u53e4\u81ea\u6cbb\u533a\u4eba\u6c11\u653f\u5e9c\u6279\u51c6\uff0c\u56fd\u5bb6\u6559\u80b2\u90e8\u5907\u6848\uff0c\u6210\u4e3a\u5168\u65e5\u5236\u516c\u529e\u666e\u901a\u9ad8\u7b49\u804c\u4e1a\u5b66\u6821\uff0c\u5e76\u4e8e2007\u5e74\u4e0e\u5185\u8499\u53e4\u51b6\u91d1\u9ad8\u7ea7\u6280\u5de5\u5b66\u6821\u5408\u5e76\u30022019\u5e745\u6708\uff0c\u5185\u8499\u53e4\u81ea\u6cbb\u533a\u4eba\u6c11\u653f\u5e9c\u6279\u590d\u5185\u8499\u53e4\u51b6\u91d1\u9ad8\u7ea7\u6280\u5de5\u5b66\u6821\u5347\u7ea7\u4e3a\u5185\u8499\u53e4\u51b6\u91d1\u6280\u5e08\u5b66\u9662\uff0c\u6807\u5fd7\u7740\u5305\u5934\u5e02\u9996\u5bb6\u6280\u5e08\u5b66\u9662\u8bde\u751f\uff0c\u5b66\u9662\u6210", "video": {}, "video_pc": {"school_id": "1631", "url": "", "url_type": "2", "img_url": "https:\\/\\/static-data.eol.cn\\/\\/upload\\/svideo\\/1611801972_2205_thumb.jpg"}, "is_video": 1, "dualclass": [], "special": [{"id": "1734160", "school_id": "1631", "special_id": "9161", "nation_feature": "2", "province_feature": "2", "is_important": "2", "limit_year": "\u4e09\u5e74", "year": "2022", "level3_weight": "0", "is_video": 2, "special_name": "\u673a\u68b0\u5236\u9020\u53ca\u81ea\u52a8\u5316\uff08\u667a\u80fd\u5de5\u4e1a\u8bbe\u8ba1\u65b9\u5411\uff09", "level_name": "\u4e13\u79d1"}, {"id": "1619484", "school_id": "1631", "special_id": "9025", "nation_feature": "2", "province_feature": "2", "is_important": "2", "limit_year": "\u4e09\u5e74", "year": "2022", "level3_weight": "0", "is_video": 2, "special_name": "\u98df\u54c1\u8425\u517b\u4e0e\u5065\u5eb7", "level_name": "\u4e13\u79d1"}, {"id": "1619486", "school_id": "1631", "special_id": "9085", "nation_feature": "2", "province_feature": "2", "is_important": "2", "limit_year": "\u4e09\u5e74", "year": "2022", "level3_weight": "0", "is_video": 2, "special_name": "\u5927\u6570\u636e\u4e0e\u4f1a\u8ba1", "level_name": "\u4e13\u79d1"}, {"id": "1619488", "school_id": "1631", "special_id": "9086", "nation_feature": "2", "province_feature": "2", "is_important": "2", "limit_year": "\u4e09\u5e74", "year": "2022", "level3_weight": "0", "is_video": 2, "special_name": "\u5927\u6570\u636e\u4e0e\u5ba1\u8ba1", "level_name": "\u4e13\u79d1"}, {"id": "1619495", "school_id": "1631", "special_id": "519", "nation_feature": "2", "province_feature": "2", "is_important": "2", "limit_year": "\u4e09\u5e74", "year": "2022", "level3_weight": "0", "is_video": 2, "special_name": "\u5efa\u7b51\u88c5\u9970\u5de5\u7a0b\u6280\u672f", "level_name": "\u4e13\u79d1"}, {"id": "1619496", "school_id": "1631", "special_id": "8971", "nation_feature": "2", "province_feature": "2", "is_important": "2", "limit_year": "\u4e09\u5e74", "year": "2022", "level3_weight": "0", "is_video": 2, "special_name": "\u5efa\u7b51\u6d88\u9632\u6280\u672f", "level_name": "\u4e13\u79d1"}, {"id": "1619498", "school_id": "1631", "special_id": "9099", "nation_feature": "2", "province_feature": "2", "is_important": "2", "limit_year": "\u4e09\u5e74", "year": "2022", "level3_weight": "0", "is_video": 2, "special_name": "\u9152\u5e97\u7ba1\u7406\u4e0e\u6570\u5b57\u5316\u8fd0\u8425", "level_name": "\u4e13\u79d1"}, {"id": "1619500", "school_id": "1631", "special_id": "9163", "nation_feature": "2", "province_feature": "2", "is_important": "2", "limit_year": "\u4e09\u5e74", "year": "2022", "level3_weight": "0", "is_video": 2, "special_name": "\u667a\u80fd\u5236\u9020\u88c5\u5907\u6280\u672f", "level_name": "\u4e13\u79d1"}, {"id": "1619501", "school_id": "1631", "special_id": "9166", "nation_feature": "2", "province_feature": "2", "is_important": "2", "limit_year": "\u4e09\u5e74", "year": "2022", "level3_weight": "0", "is_video": 2, "special_name": "\u6c7d\u8f66\u5236\u9020\u4e0e\u8bd5\u9a8c\u6280\u672f", "level_name": "\u4e13\u79d1"}, {"id": "1472314", "school_id": "1631", "special_id": "8961", "nation_feature": "2", "province_feature": "2", "is_important": "2", "limit_year": "\u4e09\u5e74", "year": "2022", "level3_weight": "0", "is_video": 2, "special_name": "\u7a00\u571f\u6750\u6599\u6280\u672f", "level_name": "\u4e13\u79d1"}], "nature_name": "\u516c\u529e", "province_score_min": {"14": {"school_id": "1631", "province_id": "14", "type": "1", "min": "130.00", "year": "2021"}, "15": {"school_id": "1631", "province_id": "15", "type": "2", "min": "162.00", "year": "2021"}, "53": {"school_id": "1631", "province_id": "53", "type": "2", "min": "386.00", "year": "2021"}, "62": {"school_id": "1631", "province_id": "62", "type": "1", "min": "160.00", "year": "2021"}, "13": {"school_id": "1631", "province_id": "13", "type": "1", "min": "316.00", "year": "2020"}, "52": {"school_id": "1631", "province_id": "52", "type": "1", "min": "385.00", "year": "2020"}}, "pro_type_min": {"14": [{"year": 2021, "type": {"1": "130.00"}}, {"year": 2020, "type": {"1": "130.00"}}, {"year": 2019, "type": {"1": "130.00"}}], "15": [{"year": 2021, "type": {"2": "162.00", "1": "160.00"}}, {"year": 2019, "type": {"32": "187.00", "1": "172.00", "2": "164.00", "33": "155.00"}}], "53": [{"year": 2021, "type": {"2": "386.00"}}, {"year": 2020, "type": {"2": "378.00", "1": "342.00"}}], "62": [{"year": 2021, "type": {"1": "160.00", "2": "160.00"}}, {"year": 2019, "type": {"2": "160.00", "1": "160.00"}}], "13": [{"year": 2020, "type": {"1": "316.00"}}, {"year": 2019, "type": {"1": "200.00"}}], "52": [{"year": 2020, "type": {"1": "385.00"}}, {"year": 2019, "type": {"2": "434.00"}}]}, "pro_type": {"14": ["1"], "15": ["2", "1", "32", "33"], "53": ["2", "1"], "62": ["1", "2"], "13": ["1"], "52": ["1", "2"]}, "province_score_year": "2021", "qs_world": "0", "rank": {"ruanke_rank": "0", "xyh_rank": "0", "wsl_rank": "0", "qs_world": "0", "us_rank": "0", "rk_mb": "0", "rk_dl": "0", "rk_zw": "0", "rk_yy": "0", "rk_cj": "0", "rk_yuy": "0", "rk_zf": "0", "rk_ty": "0", "rk_mz": "0", "xyh_gz_1": "0", "xyh_gz_2": "0", "xyh_gz_3": "0", "xyh_mb_1": "0", "xyh_mb_2": "0", "xyh_mb_3": "0", "tws_china": "0", "qs_rank": "0", "eol_rank": "2028"}, "fenxiao": [], "gbh_url": "https:\\/\\/heec.cahe.edu.cn\\/school\\/2092", "gbh_num": "0"}, "md5": "4b74951de5c212eda4eeef9290bd41c8"}